{"cameraMode":{"drawMode":0,"name":"Shaded","section":"Shading Mode"},"sceneLighting":false,"audioPlay":false,"sceneViewState":{"m_AlwaysRefresh":false,"showFog":true,"showSkybox":false,"showFlares":true,"showImageEffects":true,"showParticleSystems":true,"showVisualEffectGraphs":true,"m_FxEnabled":true},"in2DMode":false,"pivot":{"x":3.083073854446411,"y":0.15964408218860627,"z":6.885453224182129},"rotation":{"x":0.20137421786785127,"y":-0.7508214116096497,"z":0.2650105357170105,"w":0.5705304741859436},"size":0.8660253882408142,"orthographic":false}